django_fluo_legal-1.0a0.dist-info/DESCRIPTION.rst
django_fluo_legal-1.0a0.dist-info/LICENSE.txt
django_fluo_legal-1.0a0.dist-info/METADATA
django_fluo_legal-1.0a0.dist-info/RECORD
django_fluo_legal-1.0a0.dist-info/WHEEL
django_fluo_legal-1.0a0.dist-info/metadata.json
django_fluo_legal-1.0a0.dist-info/top_level.txt
legal/__init__.py
legal/admin.py
legal/apps.py
legal/forms.py
legal/models.py
legal/urls.py
legal/version.py
legal/views.py
legal/locale/en/LC_MESSAGES/django.mo
legal/locale/en/LC_MESSAGES/django.po
legal/locale/it/LC_MESSAGES/django.mo
legal/locale/it/LC_MESSAGES/django.po
legal/migrations/0001_initial.py
legal/migrations/__init__.py
legal/templates/legal/cookielaw.css
legal/templates/legal/cookielaw.html
legal/templates/legal/cookielaw.js
legal/templates/legal/cookielaw_tag.html
legal/templatetags/__init__.py
legal/templatetags/legal_tags.py
